Metadata-Version: 1.1
Name: Restcomm-Python-SDk
Version: 1.3.2
Summary: Restcomm SDk for Python user
Home-page: https://github.com/mdsharique/restcomm-sdk-python
Author: MD Sharique
Author-email: nukles1.07@gmail.com
License: MIT
Keywords: Restcomm SDk for python
Platform: UNKNOWN
Classifier: Development Status :: 5 - Production/Stable
Classifier: License :: OSI Approved :: MIT License
Classifier: Programming Language :: Python :: 3.0
Classifier: Programming Language :: Python :: 3.1
Classifier: Programming Language :: Python :: 3.2
Classifier: Programming Language :: Python :: 3.3
Classifier: Programming Language :: Python :: 3.4
Classifier: Programming Language :: Python :: 3.5
